py_noaa/__init__.py
py_noaa/coops.py
py_noaa-1.0.dist-info/LICENSE
py_noaa-1.0.dist-info/METADATA
py_noaa-1.0.dist-info/WHEEL
py_noaa-1.0.dist-info/top_level.txt
py_noaa-1.0.dist-info/RECORD
