Metadata-Version: 2.1
Name: py-noaa
Version: 1.0
Summary: Python wrapper to fetch data from NOAA APIs
Home-page: https://github.com/GClunies/py_noaa
Author: Greg Clunies
Author-email: greg.clunies@gmail.com
License: MIT
Platform: UNKNOWN
Classifier: Development Status :: 3 - Alpha
Classifier: Intended Audience :: Science/Research
Classifier: Topic :: Scientific/Engineering
Classifier: License :: OSI Approved :: MIT License
Classifier: Programming Language :: Python :: 2.7
Classifier: Programming Language :: Python :: 3.5
Classifier: Programming Language :: Python :: 3.6
Requires-Dist: requests
Requires-Dist: numpy
Requires-Dist: pandas
